ovos_skill_moon_game/README.md
ovos_skill_moon_game/__init__.py
ovos_skill_moon_game/version.py
ovos_skill_moon_game/locale/en-us/CodeResetKeyword.voc
ovos_skill_moon_game/locale/en-us/MoonGameKeyword.voc
ovos_skill_moon_game/locale/en-us/abortKeyword.voc
ovos_skill_moon_game/locale/en-us/already_equipped.dialog
ovos_skill_moon_game/locale/en-us/bad.code.dialog
ovos_skill_moon_game/locale/en-us/boardKeyword.voc
ovos_skill_moon_game/locale/en-us/boarding.dialog
ovos_skill_moon_game/locale/en-us/boarding_dead.dialog
ovos_skill_moon_game/locale/en-us/boarding_fail.dialog
ovos_skill_moon_game/locale/en-us/bootsKeyword.voc
ovos_skill_moon_game/locale/en-us/briefing.dialog
ovos_skill_moon_game/locale/en-us/briefing_end.dialog
ovos_skill_moon_game/locale/en-us/briefing_harsh.dialog
ovos_skill_moon_game/locale/en-us/briefing_lets_do_this.dialog
ovos_skill_moon_game/locale/en-us/briefing_other.dialog
ovos_skill_moon_game/locale/en-us/briefing_percentage.dialog
ovos_skill_moon_game/locale/en-us/briefing_question.dialog
ovos_skill_moon_game/locale/en-us/briefing_question2.dialog
ovos_skill_moon_game/locale/en-us/briefing_silence.dialog
ovos_skill_moon_game/locale/en-us/briefing_speech.dialog
ovos_skill_moon_game/locale/en-us/briefing_terrible.dialog
ovos_skill_moon_game/locale/en-us/briefing_warm.dialog
ovos_skill_moon_game/locale/en-us/code.reset.dialog
ovos_skill_moon_game/locale/en-us/code_dead.dialog
ovos_skill_moon_game/locale/en-us/code_enter_number.dialog
ovos_skill_moon_game/locale/en-us/code_invalid.dialog
ovos_skill_moon_game/locale/en-us/code_one_at_time.dialog
ovos_skill_moon_game/locale/en-us/codes.dialog
ovos_skill_moon_game/locale/en-us/collin_calm.dialog
ovos_skill_moon_game/locale/en-us/collin_dead.dialog
ovos_skill_moon_game/locale/en-us/collin_no.dialog
ovos_skill_moon_game/locale/en-us/collin_other.dialog
ovos_skill_moon_game/locale/en-us/collin_yes.dialog
ovos_skill_moon_game/locale/en-us/dothisKeyword.voc
ovos_skill_moon_game/locale/en-us/equip.dialog
ovos_skill_moon_game/ovos_skill_moon_game.egg-info/PKG-INFO
ovos_skill_moon_game/ovos_skill_moon_game.egg-info/SOURCES.txt
ovos_skill_moon_game/ovos_skill_moon_game.egg-info/dependency_links.txt
ovos_skill_moon_game/ovos_skill_moon_game.egg-info/entry_points.txt
ovos_skill_moon_game/ovos_skill_moon_game.egg-info/requires.txt
ovos_skill_moon_game/ovos_skill_moon_game.egg-info/top_level.txt
ovos_skill_moon_game-0.0.2.dist-info/METADATA
ovos_skill_moon_game-0.0.2.dist-info/WHEEL
ovos_skill_moon_game-0.0.2.dist-info/entry_points.txt
ovos_skill_moon_game-0.0.2.dist-info/top_level.txt
ovos_skill_moon_game-0.0.2.dist-info/RECORD
