Metadata-Version: 2.1
Name: ovos-skill-moon-game
Version: 0.0.2
Summary: Apollo11GameSkill
Home-page: https://github.com/OpenVoiceOS/ovos-skill-moon-game
Author: OpenVoiceOS
Author-email: jarbasai@mailfence.com
License: Apache2.0
Keywords: ovos skill plugin
Platform: UNKNOWN
Requires-Dist: ovos-workshop>=3.2.0
